{"stats":{"minecraft:used":{"mobpvp:pvp_spawner_item":2,"mobpvp:pvp_spawner_max_item":2},"minecraft:dropped":{"minecraft:dragon_egg":5},"minecraft:killed":{"mobpvp:mini_iron_golem":1},"minecraft:custom":{"minecraft:jump":4,"minecraft:time_since_rest":2948,"minecraft:damage_dealt":210,"minecraft:leave_game":1,"minecraft:crouch_one_cm":265,"minecraft:play_time":2948,"minecraft:time_since_death":2948,"minecraft:walk_one_cm":4196,"minecraft:sneak_time":249,"minecraft:total_world_time":12909,"minecraft:mob_kills":1,"minecraft:drop":5,"minecraft:fly_one_cm":3549},"minecraft:picked_up":{"mobpvp:hearth_part":1,"minecraft:gold_nugget":1}},"DataVersion":3955}